[{"pk": 1, "model": "contenttypes.contenttype", "fields": {"model": "logentry", "name": "log entry", "app_label": "admin"}}, {"pk": 2, "model": "contenttypes.contenttype", "fields": {"model": "permission", "name": "permission", "app_label": "auth"}}, {"pk": 3, "model": "contenttypes.contenttype", "fields": {"model": "group", "name": "group", "app_label": "auth"}}, {"pk": 4, "model": "contenttypes.contenttype", "fields": {"model": "user", "name": "user", "app_label": "auth"}}, {"pk": 5, "model": "contenttypes.contenttype", "fields": {"model": "contenttype", "name": "content type", "app_label": "contenttypes"}}, {"pk": 6, "model": "contenttypes.contenttype", "fields": {"model": "session", "name": "session", "app_label": "sessions"}}, {"pk": 7, "model": "contenttypes.contenttype", "fields": {"model": "language", "name": "language", "app_label": "dld"}}, {"pk": "r94ujz0ctrgixo6bi5s19iphvjdaq7qt", "model": "sessions.session", "fields": {"expire_date": "2014-02-26T14:25:26.997Z", "session_data": "MmY2NTFhNDExNTg0NWZkYTA5NWQ2NTNmZjliOWQzNmQzOWFhOTBmYjp7Il9hdXRoX3VzZXJfYmFja2VuZCI6ImRqYW5nby5jb250cmliLmF1dGguYmFja2VuZHMuTW9kZWxCYWNrZW5kIiwiX2F1dGhfdXNlcl9pZCI6MX0="}}, {"pk": "eng", "model": "dld.language", "fields": {"last_updated": "2014-02-12T14:26:08Z", "name2": "angol", "name": "English", "l1_speakers": {"eth": [25, 45]}}}, {"pk": "ger", "model": "dld.language", "fields": {"last_updated": "2014-02-12T14:38:01Z", "name2": "n\u00e9met", "name": "German", "l1_speakers": {"ethnologue": ["80M", 2]}}}, {"pk": "hun", "model": "dld.language", "fields": {"last_updated": "2014-03-20T14:38:49Z", "name2": "magyar", "name": "Hungarian", "l1_speakers": {}}}, {"pk": 1, "model": "auth.permission", "fields": {"codename": "add_logentry", "name": "Can add log entry", "content_type": 1}}, {"pk": 2, "model": "auth.permission", "fields": {"codename": "change_logentry", "name": "Can change log entry", "content_type": 1}}, {"pk": 3, "model": "auth.permission", "fields": {"codename": "delete_logentry", "name": "Can delete log entry", "content_type": 1}}, {"pk": 4, "model": "auth.permission", "fields": {"codename": "add_permission", "name": "Can add permission", "content_type": 2}}, {"pk": 5, "model": "auth.permission", "fields": {"codename": "change_permission", "name": "Can change permission", "content_type": 2}}, {"pk": 6, "model": "auth.permission", "fields": {"codename": "delete_permission", "name": "Can delete permission", "content_type": 2}}, {"pk": 7, "model": "auth.permission", "fields": {"codename": "add_group", "name": "Can add group", "content_type": 3}}, {"pk": 8, "model": "auth.permission", "fields": {"codename": "change_group", "name": "Can change group", "content_type": 3}}, {"pk": 9, "model": "auth.permission", "fields": {"codename": "delete_group", "name": "Can delete group", "content_type": 3}}, {"pk": 10, "model": "auth.permission", "fields": {"codename": "add_user", "name": "Can add user", "content_type": 4}}, {"pk": 11, "model": "auth.permission", "fields": {"codename": "change_user", "name": "Can change user", "content_type": 4}}, {"pk": 12, "model": "auth.permission", "fields": {"codename": "delete_user", "name": "Can delete user", "content_type": 4}}, {"pk": 13, "model": "auth.permission", "fields": {"codename": "add_contenttype", "name": "Can add content type", "content_type": 5}}, {"pk": 14, "model": "auth.permission", "fields": {"codename": "change_contenttype", "name": "Can change content type", "content_type": 5}}, {"pk": 15, "model": "auth.permission", "fields": {"codename": "delete_contenttype", "name": "Can delete content type", "content_type": 5}}, {"pk": 16, "model": "auth.permission", "fields": {"codename": "add_session", "name": "Can add session", "content_type": 6}}, {"pk": 17, "model": "auth.permission", "fields": {"codename": "change_session", "name": "Can change session", "content_type": 6}}, {"pk": 18, "model": "auth.permission", "fields": {"codename": "delete_session", "name": "Can delete session", "content_type": 6}}, {"pk": 19, "model": "auth.permission", "fields": {"codename": "add_language", "name": "Can add language", "content_type": 7}}, {"pk": 20, "model": "auth.permission", "fields": {"codename": "change_language", "name": "Can change language", "content_type": 7}}, {"pk": 21, "model": "auth.permission", "fields": {"codename": "delete_language", "name": "Can delete language", "content_type": 7}}, {"pk": 1, "model": "auth.user", "fields": {"username": "judit", "first_name": "", "last_name": "", "is_active": true, "is_superuser": true, "is_staff": true, "last_login": "2014-02-12T14:25:26.995Z", "groups": [], "user_permissions": [], "password": "pbkdf2_sha256$12000$iiMpEQC0N8O1$QoX4Q+Qi3j5K0sRXezAQ7UzgMxCEa54BoJSzCi3wD3Q=", "email": "", "date_joined": "2014-02-12T14:25:10.171Z"}}, {"pk": 1, "model": "admin.logentry", "fields": {"action_flag": 1, "action_time": "2014-02-12T14:26:20.185Z", "object_repr": "Language object", "object_id": "eng", "change_message": "", "user": 1, "content_type": 7}}, {"pk": 2, "model": "admin.logentry", "fields": {"action_flag": 2, "action_time": "2014-02-12T14:33:43.714Z", "object_repr": "Language object", "object_id": "eng", "change_message": "Changed l1_speakers.", "user": 1, "content_type": 7}}, {"pk": 3, "model": "admin.logentry", "fields": {"action_flag": 1, "action_time": "2014-02-12T14:38:35.740Z", "object_repr": "Language object", "object_id": "ger", "change_message": "", "user": 1, "content_type": 7}}, {"pk": 4, "model": "admin.logentry", "fields": {"action_flag": 1, "action_time": "2014-02-12T14:38:51.532Z", "object_repr": "Language object", "object_id": "hun", "change_message": "", "user": 1, "content_type": 7}}]